unpaac/__init__.py
unpaac/from_csv.py
unpaac/uncrts.py
unpaac-0.1.4.dist-info/LICENSE
unpaac-0.1.4.dist-info/METADATA
unpaac-0.1.4.dist-info/WHEEL
unpaac-0.1.4.dist-info/RECORD
