Metadata-Version: 2.3
Name: unpaac
Version: 0.1.4
Summary: Pandas DataFrame and Series accessors to handle quantities with uncertainties.
License: MIT
Keywords: physical,quantities,unit,conversion,error propagation,uncertainties,uncertainty,uncertainty calculations,standard deviation,science,pandas,series,dataframe
Author: Christian Schreinemachers (Cs137)
Requires-Python: >=3.9
Classifier: Intended Audience :: Education
Classifier: Intended Audience :: Science/Research
Classifier: License :: OSI Approved :: MIT License
Classifier: Programming Language :: Python :: 3
Classifier: Programming Language :: Python :: 3.9
Classifier: Programming Language :: Python :: 3.10
Classifier: Programming Language :: Python :: 3.11
Classifier: Programming Language :: Python :: 3.12
Classifier: Programming Language :: Python :: 3.13
Classifier: Programming Language :: Python :: 3 :: Only
Classifier: Topic :: Education
Classifier: Topic :: Scientific/Engineering
Requires-Dist: pint (>=0.24.4,<0.25.0)
Requires-Dist: pint-pandas (>=0.7.1,<0.8.0)
Requires-Dist: uncertainties (>=3.2.2,<4.0.0)
Requires-Dist: uncertainties-pandas (>=0.1.2,<0.2.0)
Project-URL: Changelog, https://codeberg.org/Cs137/UnPaAc/src/branch/main/CHANGELOG.md
Project-URL: Issues, https://codeberg.org/Cs137/UnPaAc/issues
Project-URL: repository, https://codeberg.org/Cs137/UnPaAc
